iland/__init__.py
iland/api.py
iland/constant.py
iland/exception.py
iland/log.py
iland_sdk-1.0.4.dist-info/AUTHORS.rst
iland_sdk-1.0.4.dist-info/LICENSE
iland_sdk-1.0.4.dist-info/METADATA
iland_sdk-1.0.4.dist-info/WHEEL
iland_sdk-1.0.4.dist-info/top_level.txt
iland_sdk-1.0.4.dist-info/RECORD
