Metadata-Version: 2.1
Name: iland-sdk
Version: 1.0.4
Summary: iland cloud Python SDK.
Home-page: https://github.com/ilanddev/python-sdk
Author: iland Internet Solutions, Corp
Author-email: devops@iland.com
License: BSD
Keywords: iland cloud sdk
Platform: UNKNOWN
Classifier: Development Status :: 5 - Production/Stable
Classifier: Intended Audience :: Developers
Classifier: License :: OSI Approved :: BSD License
Classifier: Natural Language :: English
Classifier: Programming Language :: Python :: 2
Classifier: Programming Language :: Python :: 2.7
Classifier: Programming Language :: Python :: 3
Classifier: Programming Language :: Python :: 3.4
Classifier: Programming Language :: Python :: 3.5
Classifier: Programming Language :: Python :: 3.6
Classifier: Programming Language :: Python :: 3.7
Classifier: Programming Language :: Python :: 3.8
Requires-Dist: requests (>=2.2.1)
